{
  "自动编队-启动": {
    "action": {
      "type": "Click",
      "param": {
        "target": [104, 832, 43, 48]
      }
    },
    "next": ["自动编队-清空队列-启动"]
  },
  "自动编队-清空队列-启动": {
    "recognition": {
      "type": "OCR",
      "param": {
        "expected": ["队"],
        "roi": [297, 121, 124, 61]
      }
    },
    "next": ["自动编队-清空队列-已完成", "[JumpBack]自动编队-点击清空队列"]
  },
  "自动编队-点击清空队列": {
    "action": {
      "type": "Click",
      "param": {
        "target": [75, 430, 45, 50]
      }
    },
    "post_delay": 500
  },
  "自动编队-清空队列-已完成": {
    "recognition": {
      "type": "TemplateMatch",
      "param": {
        "template": ["copilot/formation/empty.png"],
        "roi": [168, 366, 114, 166]
      }
    },
    "next": ["自动编队-开始编队", "自动编队-命盘检测-启动"]
  },
  "自动编队-开始编队": {
    "action": {
      "type": "Custom",
      "param": {
        "custom_action": "AutoFormation",
        "custom_action_param": {
          "resource": "base"
        }
      }
    },
    "next": ["自动编队-命盘检测-启动"]
  },
  "自动编队-命盘检测-启动": {
    "next": ["自动编队-命盘检测-进入属性页"]
  },
  "自动编队-命盘检测-进入属性页": {
    "action": {
      "type": "LongPress",
      "param": {
        "target": [78, 429, 45, 56],
        "duration": 3000
      }
    },
    "post_delay": 2000,
    "next": ["自动编队-命盘检测-进入命盘页"]
  },
  "自动编队-命盘检测-进入命盘页": {
    "recognition": {
      "type": "OCR",
      "param": {
        "expected": "密探列表",
        "roi": [561, 759, 158, 116]
      }
    },
    "action": {
      "type": "Click",
      "param": {
        "target": [602, 1070, 25, 22]
      }
    },
    "post_delay": 2000,
    "next": ["自动编队-命盘检测-已在命盘页"]
  },
  "自动编队-命盘检测-已在命盘页": {
    "recognition": {
      "type": "OCR",
      "param": {
        "expected": ["石"],
        "roi": [262, 616, 215, 148]
      }
    },
    "next": ["自动编队-开始命盘检测"]
  },
  "自动编队-开始命盘检测": {
    "action": {
      "type": "Custom",
      "param": {
        "custom_action": "DiscChecker",
        "custom_action_param": {
          "resource": "base"
        }
      }
    },
    "next": ["自动编队-结束命盘检测"]
  },
  "自动编队-结束命盘检测": {
    "recognition": {
      "type": "TemplateMatch",
      "param": {
        "template": ["back.png"],
        "roi": [36, 36, 62, 61],
        "green_mask": true,
        "threshold": 0.4
      }
    },
    "pre_delay": 500,
    "action": {
      "type": "Click"
    },
    "post_delay": 3000,
    "next": ["自动编队-结束命盘检测-2"]
  },
  "自动编队-结束命盘检测-2": {
    "recognition": {
      "type": "OCR",
      "param": {
        "expected": "密探列表",
        "roi": [561, 759, 158, 116]
      }
    },
    "pre_delay": 500,
    "action": {
      "type": "Click",
      "param": {
        "target": "自动编队-结束命盘检测"
      }
    },
    "post_delay": 3000
  },
  "自动编队-第一位为空": {
    "recognition": {
      "type": "TemplateMatch",
      "param": {
        "template": ["copilot/formation/empty.png"],
        "roi": [38, 353, 117, 180]
      }
    }
  },
  "自动编队-移除一号位": {
    "action": {
      "type": "Click",
      "param": {
        "target": [85, 451, 34, 31]
      }
    },
    "post_delay": 500
  },
  "自动编队-打开筛选面板": {
    "action": {
      "type": "Click",
      "param": {
        "target": [624, 781, 21, 12]
      }
    },
    "post_delay": 1000,
    "next": ["自动编队-重置筛选面板"]
  },
  "自动编队-重置筛选面板": {
    "recognition": {
      "type": "OCR",
      "param": {
        "expected": ["重置"],
        "roi": [160, 777, 94, 82]
      }
    },
    "pre_delay": 500,
    "action": {
      "type": "Click",
      "param": {}
    },
    "post_delay": 500,
    "next": ["自动编队-筛选-属性"]
  },
  "自动编队-筛选-属性": {
    "action": {
      "type": "Click",
      "param": {}
    },
    "post_delay": 500,
    "next": ["自动编队-筛选-职业"]
  },
  "自动编队-筛选-职业": {
    "action": {
      "type": "Click",
      "param": {}
    },
    "post_delay": 500,
    "next": ["自动编队-确认筛选条件"]
  },
  "自动编队-确认筛选条件": {
    "action": {
      "type": "Click",
      "param": {
        "target": [494, 815, 27, 12]
      }
    },
    "post_delay": 1000
  },
  "自动编队-重置列表滚动位置": {
    "action": {
      "type": "Swipe",
      "param": {
        "begin": [545, 878, 1, 1],
        "end": [545, 1258, 1, 1],
        "duration": 100
      }
    },
    "post_delay": 2000
  },
  "自动编队-点击目标密探": {
    "recognition": {
      "type": "Custom",
      "param": {
        "custom_recognition": "OCRWithSimilarity",
        "custom_recognition_param": {
          "resource": "base"
        }
      }
    },
    "pre_delay": 500,
    "action": {
      "type": "Click",
      "param": {
        "target_offset": [0, -50, 0, 0]
      }
    },
    "post_delay": 500
  },
  "自动编队-识别目标密探": {
    "recognition": {
      "type": "OCR",
      "param": {}
    }
  },
  "ocrtest": {
    "recognition": {
      "type": "OCR",
      "param": {
        "expected": ["马超"],
        "roi": [26, 821, 666, 241]
      }
    }
  },
  "自动编队-读取生效中命盘": {
    "recognition": {
      "type": "OCR",
      "param": {
        "expected": ["生效中"],
        "roi": [13, 201, 695, 698]
      }
    }
  },
  "自动编队-尝试切换命盘": {
    "action": {
      "type": "Click",
      "param": {
        "target": [65, 156, 52, 19]
      }
    }
  },
  "自动编队-关闭命盘提示": {
    "recognition": {
      "type": "OCR",
      "param": {
        "expected": ["定"],
        "roi": [405, 685, 200, 171]
      }
    },
    "pre_delay": 500,
    "action": {
      "type": "Click",
      "param": {
        "target": [190, 764, 43, 15]
      }
    },
    "post_delay": 2000,
    "timeout": 1000
  },
  "自动编队-命盘检测-向右切换": {
    "action": {
      "type": "Click",
      "param": {
        "target": [687, 547, 2, 2]
      }
    },
    "post_delay": 1000
  }
}
